{
    "MyGrades": [
        {
            "Semester": "Semestr 3 - zimowy 2024/2025",
            "Structure": "Struktura: WIiT - I - Ist - S",
            "Grades": [
                {
                    "SubjectName": "Język angielski",
                    "Records": [
                        {
                            "Forma zajęć": "L",
                            "Typ przedmiotu": "",
                            "Podtyp przedmiotu": "",
                            "Forma zaliczenia": "Z",
                            "Prowadzący": "mgr Katarzyna Zawadzka",
                            "Punkty ECTS": "0",
                            "Punkty ECTS za ostatnią ocenę": "90",
                            "Liczba godzin": "60",
                            "Zaliczony": "",
                            "Termin I": "5,0",
                            "Poprawkowy": "",
                            "Komis": "",
                            "Pow. przedm. I": "",
                            "Pow. przedm. II": "",
                            "Powt. przedm. poprawka": "",
                            "Powt. przedm. komis": "",
                            "Komis dziekański": "",
                            "Powt. przedm. II poprawka": "",
                            "Powt. przedm. II komis": ""
                        },
                        {
                            "Forma zajęć": "K",
                            "Typ przedmiotu": "",
                            "Podtyp przedmiotu": "",
                            "Forma zaliczenia": "KO",
                            "Prowadzący": "mgr Katarzyna Zawadzka",
                            "Punkty ECTS": "2",
                            "Punkty ECTS za ostatnią ocenę": "90",
                            "Liczba godzin": "0",
                            "Zaliczony": "",
                            "Termin I": "5,0",
                            "Poprawkowy": "",
                            "Komis": "",
                            "Pow. przedm. I": "",
                            "Pow. przedm. II": "",
                            "Powt. przedm. poprawka": "",
                            "Powt. przedm. komis": "",
                            "Komis dziekański": "",
                            "Powt. przedm. II poprawka": "",
                            "Powt. przedm. II komis": ""
                        }
                    ]
                },
                {
                    "SubjectName": "Wychowanie fizyczne",
                    "Records": [
                        {
                            "Forma zajęć": "L",
                            "Typ przedmiotu": "",
                            "Podtyp przedmiotu": "",
                            "Forma zaliczenia": "Z",
                            "Prowadzący": "mgr Norbert Marchewka",
                            "Punkty ECTS": "0",
                            "Punkty ECTS za ostatnią ocenę": "90",
                            "Liczba godzin": "15",
                            "Zaliczony": "",
                            "Termin I": "5,0",
                            "Poprawkowy": "",
                            "Komis": "",
                            "Pow. przedm. I": "",
                            "Pow. przedm. II": "",
                            "Powt. przedm. poprawka": "",
                            "Powt. przedm. komis": "",
                            "Komis dziekański": "",
                            "Powt. przedm. II poprawka": "",
                            "Powt. przedm. II komis": ""
                        },
                        {
                            "Forma zajęć": "K",
                            "Typ przedmiotu": "",
                            "Podtyp przedmiotu": "",
                            "Forma zaliczenia": "KO",
                            "Prowadzący": "mgr Norbert Marchewka",
                            "Punkty ECTS": "0",
                            "Punkty ECTS za ostatnią ocenę": "90",
                            "Liczba godzin": "0",
                            "Zaliczony": "",
                            "Termin I": "5,0",
                            "Poprawkowy": "",
                            "Komis": "",
                            "Pow. przedm. I": "",
                            "Pow. przedm. II": "",
                            "Powt. przedm. poprawka": "",
                            "Powt. przedm. komis": "",
                            "Komis dziekański": "",
                            "Powt. przedm. II poprawka": "",
                            "Powt. przedm. II komis": ""
                        }
                    ]
                },
                {
                    "SubjectName": "Matematyka dyskretna",
                    "Records": [
                        {
                            "Forma zajęć": "A",
                            "Typ przedmiotu": "",
                            "Podtyp przedmiotu": "",
                            "Forma zaliczenia": "E",
                            "Prowadzący": "dr hab. inż. Marek Landowski",
                            "Punkty ECTS": "0",
                            "Punkty ECTS za ostatnią ocenę": "0",
                            "Liczba godzin": "30",
                            "Zaliczony": "",
                            "Termin I": "",
                            "Poprawkowy": "",
                            "Komis": "",
                            "Pow. przedm. I": "",
                            "Pow. przedm. II": "",
                            "Powt. przedm. poprawka": "",
                            "Powt. przedm. komis": "",
                            "Komis dziekański": "",
                            "Powt. przedm. II poprawka": "",
                            "Powt. przedm. II komis": ""
                        },
                        {
                            "Forma zajęć": "C",
                            "Typ przedmiotu": "",
                            "Podtyp przedmiotu": "",
                            "Forma zaliczenia": "Z",
                            "Prowadzący": "dr hab. inż. Marek Landowski",
                            "Punkty ECTS": "0",
                            "Punkty ECTS za ostatnią ocenę": "90",
                            "Liczba godzin": "30",
                            "Zaliczony": "",
                            "Termin I": "5,0",
                            "Poprawkowy": "",
                            "Komis": "",
                            "Pow. przedm. I": "",
                            "Pow. przedm. II": "",
                            "Powt. przedm. poprawka": "",
                            "Powt. przedm. komis": "",
                            "Komis dziekański": "",
                            "Powt. przedm. II poprawka": "",
                            "Powt. przedm. II komis": ""
                        },
                        {
                            "Forma zajęć": "K",
                            "Typ przedmiotu": "",
                            "Podtyp przedmiotu": "",
                            "Forma zaliczenia": "KO",
                            "Prowadzący": "dr hab. inż. Marek Landowski",
                            "Punkty ECTS": "7",
                            "Punkty ECTS za ostatnią ocenę": "0",
                            "Liczba godzin": "0",
                            "Zaliczony": "",
                            "Termin I": "",
                            "Poprawkowy": "",
                            "Komis": "",
                            "Pow. przedm. I": "",
                            "Pow. przedm. II": "",
                            "Powt. przedm. poprawka": "",
                            "Powt. przedm. komis": "",
                            "Komis dziekański": "",
                            "Powt. przedm. II poprawka": "",
                            "Powt. przedm. II komis": ""
                        }
                    ]
                },
                {
                    "SubjectName": "Struktury danych",
                    "Records": [
                        {
                            "Forma zajęć": "A",
                            "Typ przedmiotu": "",
                            "Podtyp przedmiotu": "",
                            "Forma zaliczenia": "Z",
                            "Prowadzący": "dr inż. Gerard Wawrzyniak",
                            "Punkty ECTS": "0",
                            "Punkty ECTS za ostatnią ocenę": "0",
                            "Liczba godzin": "15",
                            "Zaliczony": "",
                            "Termin I": "",
                            "Poprawkowy": "",
                            "Komis": "",
                            "Pow. przedm. I": "",
                            "Pow. przedm. II": "",
                            "Powt. przedm. poprawka": "",
                            "Powt. przedm. komis": "",
                            "Komis dziekański": "",
                            "Powt. przedm. II poprawka": "",
                            "Powt. przedm. II komis": ""
                        },
                        {
                            "Forma zajęć": "L",
                            "Typ przedmiotu": "",
                            "Podtyp przedmiotu": "",
                            "Forma zaliczenia": "Z",
                            "Prowadzący": "mgr inż. Filip Majewski",
                            "Punkty ECTS": "0",
                            "Punkty ECTS za ostatnią ocenę": "80",
                            "Liczba godzin": "15",
                            "Zaliczony": "",
                            "Termin I": "4,5",
                            "Poprawkowy": "",
                            "Komis": "",
                            "Pow. przedm. I": "",
                            "Pow. przedm. II": "",
                            "Powt. przedm. poprawka": "",
                            "Powt. przedm. komis": "",
                            "Komis dziekański": "",
                            "Powt. przedm. II poprawka": "",
                            "Powt. przedm. II komis": ""
                        },
                        {
                            "Forma zajęć": "K",
                            "Typ przedmiotu": "",
                            "Podtyp przedmiotu": "",
                            "Forma zaliczenia": "KO",
                            "Prowadzący": "dr inż. Gerard Wawrzyniak",
                            "Punkty ECTS": "3",
                            "Punkty ECTS za ostatnią ocenę": "0",
                            "Liczba godzin": "0",
                            "Zaliczony": "",
                            "Termin I": "",
                            "Poprawkowy": "",
                            "Komis": "",
                            "Pow. przedm. I": "",
                            "Pow. przedm. II": "",
                            "Powt. przedm. poprawka": "",
                            "Powt. przedm. komis": "",
                            "Komis dziekański": "",
                            "Powt. przedm. II poprawka": "",
                            "Powt. przedm. II komis": ""
                        }
                    ]
                },
                {
                    "SubjectName": "Metody numeryczne",
                    "Records": [
                        {
                            "Forma zajęć": "A",
                            "Typ przedmiotu": "",
                            "Podtyp przedmiotu": "",
                            "Forma zaliczenia": "Z",
                            "Prowadzący": "dr hab. inż. Marek Landowski",
                            "Punkty ECTS": "0",
                            "Punkty ECTS za ostatnią ocenę": "70",
                            "Liczba godzin": "15",
                            "Zaliczony": "",
                            "Termin I": "4,0",
                            "Poprawkowy": "",
                            "Komis": "",
                            "Pow. przedm. I": "",
                            "Pow. przedm. II": "",
                            "Powt. przedm. poprawka": "",
                            "Powt. przedm. komis": "",
                            "Komis dziekański": "",
                            "Powt. przedm. II poprawka": "",
                            "Powt. przedm. II komis": ""
                        },
                        {
                            "Forma zajęć": "L",
                            "Typ przedmiotu": "",
                            "Podtyp przedmiotu": "",
                            "Forma zaliczenia": "Z",
                            "Prowadzący": "dr hab. inż. Marek Landowski",
                            "Punkty ECTS": "0",
                            "Punkty ECTS za ostatnią ocenę": "90",
                            "Liczba godzin": "15",
                            "Zaliczony": "",
                            "Termin I": "5,0",
                            "Poprawkowy": "",
                            "Komis": "",
                            "Pow. przedm. I": "",
                            "Pow. przedm. II": "",
                            "Powt. przedm. poprawka": "",
                            "Powt. przedm. komis": "",
                            "Komis dziekański": "",
                            "Powt. przedm. II poprawka": "",
                            "Powt. przedm. II komis": ""
                        },
                        {
                            "Forma zajęć": "K",
                            "Typ przedmiotu": "",
                            "Podtyp przedmiotu": "",
                            "Forma zaliczenia": "KO",
                            "Prowadzący": "dr hab. inż. Marek Landowski",
                            "Punkty ECTS": "3",
                            "Punkty ECTS za ostatnią ocenę": "80",
                            "Liczba godzin": "0",
                            "Zaliczony": "",
                            "Termin I": "4,5",
                            "Poprawkowy": "",
                            "Komis": "",
                            "Pow. przedm. I": "",
                            "Pow. przedm. II": "",
                            "Powt. przedm. poprawka": "",
                            "Powt. przedm. komis": "",
                            "Komis dziekański": "",
                            "Powt. przedm. II poprawka": "",
                            "Powt. przedm. II komis": ""
                        }
                    ]
                },
                {
                    "SubjectName": "Programowanie obiektowe",
                    "Records": [
                        {
                            "Forma zajęć": "A",
                            "Typ przedmiotu": "",
                            "Podtyp przedmiotu": "",
                            "Forma zaliczenia": "E",
                            "Prowadzący": "dr inż. Łukasz Nozdrzykowski",
                            "Punkty ECTS": "0",
                            "Punkty ECTS za ostatnią ocenę": "0",
                            "Liczba godzin": "30",
                            "Zaliczony": "",
                            "Termin I": "",
                            "Poprawkowy": "",
                            "Komis": "",
                            "Pow. przedm. I": "",
                            "Pow. przedm. II": "",
                            "Powt. przedm. poprawka": "",
                            "Powt. przedm. komis": "",
                            "Komis dziekański": "",
                            "Powt. przedm. II poprawka": "",
                            "Powt. przedm. II komis": ""
                        },
                        {
                            "Forma zajęć": "L",
                            "Typ przedmiotu": "",
                            "Podtyp przedmiotu": "",
                            "Forma zaliczenia": "Z",
                            "Prowadzący": "mgr inż. Aleksander Wolak",
                            "Punkty ECTS": "0",
                            "Punkty ECTS za ostatnią ocenę": "0",
                            "Liczba godzin": "30",
                            "Zaliczony": "",
                            "Termin I": "",
                            "Poprawkowy": "",
                            "Komis": "",
                            "Pow. przedm. I": "",
                            "Pow. przedm. II": "",
                            "Powt. przedm. poprawka": "",
                            "Powt. przedm. komis": "",
                            "Komis dziekański": "",
                            "Powt. przedm. II poprawka": "",
                            "Powt. przedm. II komis": ""
                        },
                        {
                            "Forma zajęć": "K",
                            "Typ przedmiotu": "",
                            "Podtyp przedmiotu": "",
                            "Forma zaliczenia": "KO",
                            "Prowadzący": "dr inż. Łukasz Nozdrzykowski",
                            "Punkty ECTS": "4",
                            "Punkty ECTS za ostatnią ocenę": "0",
                            "Liczba godzin": "0",
                            "Zaliczony": "",
                            "Termin I": "",
                            "Poprawkowy": "",
                            "Komis": "",
                            "Pow. przedm. I": "",
                            "Pow. przedm. II": "",
                            "Powt. przedm. poprawka": "",
                            "Powt. przedm. komis": "",
                            "Komis dziekański": "",
                            "Powt. przedm. II poprawka": "",
                            "Powt. przedm. II komis": ""
                        }
                    ]
                },
                {
                    "SubjectName": "Sieci komputerowe",
                    "Records": [
                        {
                            "Forma zajęć": "A",
                            "Typ przedmiotu": "",
                            "Podtyp przedmiotu": "",
                            "Forma zaliczenia": "E",
                            "Prowadzący": "mgr inż. Janusz Magaj",
                            "Punkty ECTS": "0",
                            "Punkty ECTS za ostatnią ocenę": "0",
                            "Liczba godzin": "30",
                            "Zaliczony": "",
                            "Termin I": "",
                            "Poprawkowy": "",
                            "Komis": "",
                            "Pow. przedm. I": "",
                            "Pow. przedm. II": "",
                            "Powt. przedm. poprawka": "",
                            "Powt. przedm. komis": "",
                            "Komis dziekański": "",
                            "Powt. przedm. II poprawka": "",
                            "Powt. przedm. II komis": ""
                        },
                        {
                            "Forma zajęć": "L",
                            "Typ przedmiotu": "",
                            "Podtyp przedmiotu": "",
                            "Forma zaliczenia": "Z",
                            "Prowadzący": "mgr inż. Marcin Breitsprecher",
                            "Punkty ECTS": "0",
                            "Punkty ECTS za ostatnią ocenę": "0",
                            "Liczba godzin": "30",
                            "Zaliczony": "",
                            "Termin I": "",
                            "Poprawkowy": "",
                            "Komis": "",
                            "Pow. przedm. I": "",
                            "Pow. przedm. II": "",
                            "Powt. przedm. poprawka": "",
                            "Powt. przedm. komis": "",
                            "Komis dziekański": "",
                            "Powt. przedm. II poprawka": "",
                            "Powt. przedm. II komis": ""
                        },
                        {
                            "Forma zajęć": "K",
                            "Typ przedmiotu": "",
                            "Podtyp przedmiotu": "",
                            "Forma zaliczenia": "KO",
                            "Prowadzący": "mgr inż. Janusz Magaj",
                            "Punkty ECTS": "4",
                            "Punkty ECTS za ostatnią ocenę": "0",
                            "Liczba godzin": "0",
                            "Zaliczony": "",
                            "Termin I": "",
                            "Poprawkowy": "",
                            "Komis": "",
                            "Pow. przedm. I": "",
                            "Pow. przedm. II": "",
                            "Powt. przedm. poprawka": "",
                            "Powt. przedm. komis": "",
                            "Komis dziekański": "",
                            "Powt. przedm. II poprawka": "",
                            "Powt. przedm. II komis": ""
                        }
                    ]
                },
                {
                    "SubjectName": "Metody probabilistyczne i statystyka w informatyce",
                    "Records": [
                        {
                            "Forma zajęć": "A",
                            "Typ przedmiotu": "",
                            "Podtyp przedmiotu": "",
                            "Forma zaliczenia": "E",
                            "Prowadzący": "dr hab. Piotr Borkowski",
                            "Punkty ECTS": "0",
                            "Punkty ECTS za ostatnią ocenę": "50",
                            "Liczba godzin": "30",
                            "Zaliczony": "",
                            "Termin I": "3,0",
                            "Poprawkowy": "",
                            "Komis": "",
                            "Pow. przedm. I": "",
                            "Pow. przedm. II": "",
                            "Powt. przedm. poprawka": "",
                            "Powt. przedm. komis": "",
                            "Komis dziekański": "",
                            "Powt. przedm. II poprawka": "",
                            "Powt. przedm. II komis": ""
                        },
                        {
                            "Forma zajęć": "C",
                            "Typ przedmiotu": "",
                            "Podtyp przedmiotu": "",
                            "Forma zaliczenia": "Z",
                            "Prowadzący": "dr hab. Piotr Borkowski",
                            "Punkty ECTS": "0",
                            "Punkty ECTS za ostatnią ocenę": "50",
                            "Liczba godzin": "30",
                            "Zaliczony": "",
                            "Termin I": "3,0",
                            "Poprawkowy": "",
                            "Komis": "",
                            "Pow. przedm. I": "",
                            "Pow. przedm. II": "",
                            "Powt. przedm. poprawka": "",
                            "Powt. przedm. komis": "",
                            "Komis dziekański": "",
                            "Powt. przedm. II poprawka": "",
                            "Powt. przedm. II komis": ""
                        },
                        {
                            "Forma zajęć": "K",
                            "Typ przedmiotu": "",
                            "Podtyp przedmiotu": "",
                            "Forma zaliczenia": "KO",
                            "Prowadzący": "dr hab. Piotr Borkowski",
                            "Punkty ECTS": "7",
                            "Punkty ECTS za ostatnią ocenę": "50",
                            "Liczba godzin": "0",
                            "Zaliczony": "",
                            "Termin I": "3,0",
                            "Poprawkowy": "",
                            "Komis": "",
                            "Pow. przedm. I": "",
                            "Pow. przedm. II": "",
                            "Powt. przedm. poprawka": "",
                            "Powt. przedm. komis": "",
                            "Komis dziekański": "",
                            "Powt. przedm. II poprawka": "",
                            "Powt. przedm. II komis": ""
                        }
                    ]
                }
            ]
        },
        {
            "Semester": "Semestr 2 - letni 2023/2024",
            "Structure": "Struktura: WIiT - I - Ist - S",
            "Grades": [
                {
                    "SubjectName": "Język angielski",
                    "Records": [
                        {
                            "Forma zajęć": "L",
                            "Typ przedmiotu": "",
                            "Podtyp przedmiotu": "",
                            "Forma zaliczenia": "Z",
                            "Prowadzący": "mgr Katarzyna Zawadzka",
                            "Punkty ECTS": "0",
                            "Punkty ECTS za ostatnią ocenę": "90",
                            "Liczba godzin": "60",
                            "Zaliczony": "",
                            "Termin I": "5,0",
                            "Poprawkowy": "",
                            "Komis": "",
                            "Pow. przedm. I": "",
                            "Pow. przedm. II": "",
                            "Powt. przedm. poprawka": "",
                            "Powt. przedm. komis": "",
                            "Komis dziekański": "",
                            "Powt. przedm. II poprawka": "",
                            "Powt. przedm. II komis": ""
                        },
                        {
                            "Forma zajęć": "K",
                            "Typ przedmiotu": "",
                            "Podtyp przedmiotu": "",
                            "Forma zaliczenia": "KO",
                            "Prowadzący": "mgr Katarzyna Zawadzka",
                            "Punkty ECTS": "2",
                            "Punkty ECTS za ostatnią ocenę": "90",
                            "Liczba godzin": "0",
                            "Zaliczony": "",
                            "Termin I": "5,0",
                            "Poprawkowy": "",
                            "Komis": "",
                            "Pow. przedm. I": "",
                            "Pow. przedm. II": "",
                            "Powt. przedm. poprawka": "",
                            "Powt. przedm. komis": "",
                            "Komis dziekański": "",
                            "Powt. przedm. II poprawka": "",
                            "Powt. przedm. II komis": ""
                        }
                    ]
                },
                {
                    "SubjectName": "Wychowanie fizyczne",
                    "Records": [
                        {
                            "Forma zajęć": "L",
                            "Typ przedmiotu": "",
                            "Podtyp przedmiotu": "",
                            "Forma zaliczenia": "Z",
                            "Prowadzący": "mgr Norbert Marchewka",
                            "Punkty ECTS": "0",
                            "Punkty ECTS za ostatnią ocenę": "90",
                            "Liczba godzin": "15",
                            "Zaliczony": "",
                            "Termin I": "5,0",
                            "Poprawkowy": "",
                            "Komis": "",
                            "Pow. przedm. I": "",
                            "Pow. przedm. II": "",
                            "Powt. przedm. poprawka": "",
                            "Powt. przedm. komis": "",
                            "Komis dziekański": "",
                            "Powt. przedm. II poprawka": "",
                            "Powt. przedm. II komis": ""
                        },
                        {
                            "Forma zajęć": "K",
                            "Typ przedmiotu": "",
                            "Podtyp przedmiotu": "",
                            "Forma zaliczenia": "KO",
                            "Prowadzący": "mgr Norbert Marchewka",
                            "Punkty ECTS": "0",
                            "Punkty ECTS za ostatnią ocenę": "90",
                            "Liczba godzin": "0",
                            "Zaliczony": "",
                            "Termin I": "5,0",
                            "Poprawkowy": "",
                            "Komis": "",
                            "Pow. przedm. I": "",
                            "Pow. przedm. II": "",
                            "Powt. przedm. poprawka": "",
                            "Powt. przedm. komis": "",
                            "Komis dziekański": "",
                            "Powt. przedm. II poprawka": "",
                            "Powt. przedm. II komis": ""
                        }
                    ]
                },
                {
                    "SubjectName": "Algebra liniowa",
                    "Records": [
                        {
                            "Forma zajęć": "A",
                            "Typ przedmiotu": "",
                            "Podtyp przedmiotu": "",
                            "Forma zaliczenia": "E",
                            "Prowadzący": "mgr Sylwia Mielniczuk",
                            "Punkty ECTS": "0",
                            "Punkty ECTS za ostatnią ocenę": "90",
                            "Liczba godzin": "30",
                            "Zaliczony": "",
                            "Termin I": "5,0",
                            "Poprawkowy": "",
                            "Komis": "",
                            "Pow. przedm. I": "",
                            "Pow. przedm. II": "",
                            "Powt. przedm. poprawka": "",
                            "Powt. przedm. komis": "",
                            "Komis dziekański": "",
                            "Powt. przedm. II poprawka": "",
                            "Powt. przedm. II komis": ""
                        },
                        {
                            "Forma zajęć": "C",
                            "Typ przedmiotu": "",
                            "Podtyp przedmiotu": "",
                            "Forma zaliczenia": "Z",
                            "Prowadzący": "mgr Kinga Kuzioła",
                            "Punkty ECTS": "0",
                            "Punkty ECTS za ostatnią ocenę": "90",
                            "Liczba godzin": "30",
                            "Zaliczony": "",
                            "Termin I": "5,0",
                            "Poprawkowy": "",
                            "Komis": "",
                            "Pow. przedm. I": "",
                            "Pow. przedm. II": "",
                            "Powt. przedm. poprawka": "",
                            "Powt. przedm. komis": "",
                            "Komis dziekański": "",
                            "Powt. przedm. II poprawka": "",
                            "Powt. przedm. II komis": ""
                        },
                        {
                            "Forma zajęć": "K",
                            "Typ przedmiotu": "",
                            "Podtyp przedmiotu": "",
                            "Forma zaliczenia": "KO",
                            "Prowadzący": "mgr Sylwia Mielniczuk",
                            "Punkty ECTS": "7",
                            "Punkty ECTS za ostatnią ocenę": "90",
                            "Liczba godzin": "0",
                            "Zaliczony": "",
                            "Termin I": "5,0",
                            "Poprawkowy": "",
                            "Komis": "",
                            "Pow. przedm. I": "",
                            "Pow. przedm. II": "",
                            "Powt. przedm. poprawka": "",
                            "Powt. przedm. komis": "",
                            "Komis dziekański": "",
                            "Powt. przedm. II poprawka": "",
                            "Powt. przedm. II komis": ""
                        }
                    ]
                },
                {
                    "SubjectName": "Elektronika",
                    "Records": [
                        {
                            "Forma zajęć": "A",
                            "Typ przedmiotu": "",
                            "Podtyp przedmiotu": "",
                            "Forma zaliczenia": "Z",
                            "Prowadzący": "dr inż. Piotr Majzner",
                            "Punkty ECTS": "0",
                            "Punkty ECTS za ostatnią ocenę": "70",
                            "Liczba godzin": "30",
                            "Zaliczony": "",
                            "Termin I": "4,0",
                            "Poprawkowy": "",
                            "Komis": "",
                            "Pow. przedm. I": "",
                            "Pow. przedm. II": "",
                            "Powt. przedm. poprawka": "",
                            "Powt. przedm. komis": "",
                            "Komis dziekański": "",
                            "Powt. przedm. II poprawka": "",
                            "Powt. przedm. II komis": ""
                        },
                        {
                            "Forma zajęć": "L",
                            "Typ przedmiotu": "",
                            "Podtyp przedmiotu": "",
                            "Forma zaliczenia": "Z",
                            "Prowadzący": "mgr inż. kpt.ż.w. Wiesław Salmonowicz",
                            "Punkty ECTS": "0",
                            "Punkty ECTS za ostatnią ocenę": "80",
                            "Liczba godzin": "30",
                            "Zaliczony": "",
                            "Termin I": "4,5",
                            "Poprawkowy": "",
                            "Komis": "",
                            "Pow. przedm. I": "",
                            "Pow. przedm. II": "",
                            "Powt. przedm. poprawka": "",
                            "Powt. przedm. komis": "",
                            "Komis dziekański": "",
                            "Powt. przedm. II poprawka": "",
                            "Powt. przedm. II komis": ""
                        },
                        {
                            "Forma zajęć": "K",
                            "Typ przedmiotu": "",
                            "Podtyp przedmiotu": "",
                            "Forma zaliczenia": "KO",
                            "Prowadzący": "dr inż. Piotr Majzner",
                            "Punkty ECTS": "4",
                            "Punkty ECTS za ostatnią ocenę": "80",
                            "Liczba godzin": "0",
                            "Zaliczony": "",
                            "Termin I": "4,5",
                            "Poprawkowy": "",
                            "Komis": "",
                            "Pow. przedm. I": "",
                            "Pow. przedm. II": "",
                            "Powt. przedm. poprawka": "",
                            "Powt. przedm. komis": "",
                            "Komis dziekański": "",
                            "Powt. przedm. II poprawka": "",
                            "Powt. przedm. II komis": ""
                        }
                    ]
                },
                {
                    "SubjectName": "Metody programowania",
                    "Records": [
                        {
                            "Forma zajęć": "A",
                            "Typ przedmiotu": "",
                            "Podtyp przedmiotu": "",
                            "Forma zaliczenia": "E",
                            "Prowadzący": "dr inż. Leszek Misztal",
                            "Punkty ECTS": "0",
                            "Punkty ECTS za ostatnią ocenę": "90",
                            "Liczba godzin": "30",
                            "Zaliczony": "",
                            "Termin I": "5,0",
                            "Poprawkowy": "",
                            "Komis": "",
                            "Pow. przedm. I": "",
                            "Pow. przedm. II": "",
                            "Powt. przedm. poprawka": "",
                            "Powt. przedm. komis": "",
                            "Komis dziekański": "",
                            "Powt. przedm. II poprawka": "",
                            "Powt. przedm. II komis": ""
                        },
                        {
                            "Forma zajęć": "L",
                            "Typ przedmiotu": "",
                            "Podtyp przedmiotu": "",
                            "Forma zaliczenia": "Z",
                            "Prowadzący": "mgr inż. Mateusz Raciborski",
                            "Punkty ECTS": "0",
                            "Punkty ECTS za ostatnią ocenę": "90",
                            "Liczba godzin": "30",
                            "Zaliczony": "",
                            "Termin I": "5,0",
                            "Poprawkowy": "",
                            "Komis": "",
                            "Pow. przedm. I": "",
                            "Pow. przedm. II": "",
                            "Powt. przedm. poprawka": "",
                            "Powt. przedm. komis": "",
                            "Komis dziekański": "",
                            "Powt. przedm. II poprawka": "",
                            "Powt. przedm. II komis": ""
                        },
                        {
                            "Forma zajęć": "K",
                            "Typ przedmiotu": "",
                            "Podtyp przedmiotu": "",
                            "Forma zaliczenia": "KO",
                            "Prowadzący": "dr inż. Leszek Misztal",
                            "Punkty ECTS": "6",
                            "Punkty ECTS za ostatnią ocenę": "90",
                            "Liczba godzin": "0",
                            "Zaliczony": "",
                            "Termin I": "5,0",
                            "Poprawkowy": "",
                            "Komis": "",
                            "Pow. przedm. I": "",
                            "Pow. przedm. II": "",
                            "Powt. przedm. poprawka": "",
                            "Powt. przedm. komis": "",
                            "Komis dziekański": "",
                            "Powt. przedm. II poprawka": "",
                            "Powt. przedm. II komis": ""
                        }
                    ]
                },
                {
                    "SubjectName": "Architektura systemów komputerowych",
                    "Records": [
                        {
                            "Forma zajęć": "A",
                            "Typ przedmiotu": "",
                            "Podtyp przedmiotu": "",
                            "Forma zaliczenia": "E",
                            "Prowadzący": "mgr inż. Marcin Breitsprecher",
                            "Punkty ECTS": "0",
                            "Punkty ECTS za ostatnią ocenę": "50",
                            "Liczba godzin": "45",
                            "Zaliczony": "",
                            "Termin I": "3,0",
                            "Poprawkowy": "",
                            "Komis": "",
                            "Pow. przedm. I": "",
                            "Pow. przedm. II": "",
                            "Powt. przedm. poprawka": "",
                            "Powt. przedm. komis": "",
                            "Komis dziekański": "",
                            "Powt. przedm. II poprawka": "",
                            "Powt. przedm. II komis": ""
                        },
                        {
                            "Forma zajęć": "L",
                            "Typ przedmiotu": "",
                            "Podtyp przedmiotu": "",
                            "Forma zaliczenia": "Z",
                            "Prowadzący": "mgr inż. Janusz Magaj",
                            "Punkty ECTS": "0",
                            "Punkty ECTS za ostatnią ocenę": "70",
                            "Liczba godzin": "15",
                            "Zaliczony": "",
                            "Termin I": "4,0",
                            "Poprawkowy": "",
                            "Komis": "",
                            "Pow. przedm. I": "",
                            "Pow. przedm. II": "",
                            "Powt. przedm. poprawka": "",
                            "Powt. przedm. komis": "",
                            "Komis dziekański": "",
                            "Powt. przedm. II poprawka": "",
                            "Powt. przedm. II komis": ""
                        },
                        {
                            "Forma zajęć": "K",
                            "Typ przedmiotu": "",
                            "Podtyp przedmiotu": "",
                            "Forma zaliczenia": "KO",
                            "Prowadzący": "mgr inż. Marcin Breitsprecher",
                            "Punkty ECTS": "5",
                            "Punkty ECTS za ostatnią ocenę": "60",
                            "Liczba godzin": "0",
                            "Zaliczony": "",
                            "Termin I": "3,5",
                            "Poprawkowy": "",
                            "Komis": "",
                            "Pow. przedm. I": "",
                            "Pow. przedm. II": "",
                            "Powt. przedm. poprawka": "",
                            "Powt. przedm. komis": "",
                            "Komis dziekański": "",
                            "Powt. przedm. II poprawka": "",
                            "Powt. przedm. II komis": ""
                        }
                    ]
                },
                {
                    "SubjectName": "Systemy operacyjne",
                    "Records": [
                        {
                            "Forma zajęć": "A",
                            "Typ przedmiotu": "",
                            "Podtyp przedmiotu": "",
                            "Forma zaliczenia": "E",
                            "Prowadzący": "dr inż. Łukasz Nozdrzykowski",
                            "Punkty ECTS": "0",
                            "Punkty ECTS za ostatnią ocenę": "70",
                            "Liczba godzin": "30",
                            "Zaliczony": "",
                            "Termin I": "4,0",
                            "Poprawkowy": "",
                            "Komis": "",
                            "Pow. przedm. I": "",
                            "Pow. przedm. II": "",
                            "Powt. przedm. poprawka": "",
                            "Powt. przedm. komis": "",
                            "Komis dziekański": "",
                            "Powt. przedm. II poprawka": "",
                            "Powt. przedm. II komis": ""
                        },
                        {
                            "Forma zajęć": "L",
                            "Typ przedmiotu": "",
                            "Podtyp przedmiotu": "",
                            "Forma zaliczenia": "Z",
                            "Prowadzący": "mgr inż. Aleksander Wolak",
                            "Punkty ECTS": "0",
                            "Punkty ECTS za ostatnią ocenę": "90",
                            "Liczba godzin": "30",
                            "Zaliczony": "",
                            "Termin I": "5,0",
                            "Poprawkowy": "",
                            "Komis": "",
                            "Pow. przedm. I": "",
                            "Pow. przedm. II": "",
                            "Powt. przedm. poprawka": "",
                            "Powt. przedm. komis": "",
                            "Komis dziekański": "",
                            "Powt. przedm. II poprawka": "",
                            "Powt. przedm. II komis": ""
                        },
                        {
                            "Forma zajęć": "K",
                            "Typ przedmiotu": "",
                            "Podtyp przedmiotu": "",
                            "Forma zaliczenia": "KO",
                            "Prowadzący": "dr inż. Łukasz Nozdrzykowski",
                            "Punkty ECTS": "6",
                            "Punkty ECTS za ostatnią ocenę": "80",
                            "Liczba godzin": "0",
                            "Zaliczony": "",
                            "Termin I": "4,5",
                            "Poprawkowy": "",
                            "Komis": "",
                            "Pow. przedm. I": "",
                            "Pow. przedm. II": "",
                            "Powt. przedm. poprawka": "",
                            "Powt. przedm. komis": "",
                            "Komis dziekański": "",
                            "Powt. przedm. II poprawka": "",
                            "Powt. przedm. II komis": ""
                        }
                    ]
                }
            ]
        },
        {
            "Semester": "Semestr 1 - zimowy 2023/2024",
            "Structure": "Struktura: WIiT - I - Ist - S",
            "Grades": [
                {
                    "SubjectName": "Psychologia zachowań ludzkich",
                    "Records": [
                        {
                            "Forma zajęć": "A",
                            "Typ przedmiotu": "",
                            "Podtyp przedmiotu": "",
                            "Forma zaliczenia": "Z",
                            "Prowadzący": "dr inż. Patrycja Narękiewicz",
                            "Punkty ECTS": "0",
                            "Punkty ECTS za ostatnią ocenę": "90",
                            "Liczba godzin": "15",
                            "Zaliczony": "",
                            "Termin I": "5,0",
                            "Poprawkowy": "",
                            "Komis": "",
                            "Pow. przedm. I": "",
                            "Pow. przedm. II": "",
                            "Powt. przedm. poprawka": "",
                            "Powt. przedm. komis": "",
                            "Komis dziekański": "",
                            "Powt. przedm. II poprawka": "",
                            "Powt. przedm. II komis": ""
                        },
                        {
                            "Forma zajęć": "K",
                            "Typ przedmiotu": "",
                            "Podtyp przedmiotu": "",
                            "Forma zaliczenia": "KO",
                            "Prowadzący": "dr inż. Patrycja Narękiewicz",
                            "Punkty ECTS": "1",
                            "Punkty ECTS za ostatnią ocenę": "90",
                            "Liczba godzin": "0",
                            "Zaliczony": "",
                            "Termin I": "5,0",
                            "Poprawkowy": "",
                            "Komis": "",
                            "Pow. przedm. I": "",
                            "Pow. przedm. II": "",
                            "Powt. przedm. poprawka": "",
                            "Powt. przedm. komis": "",
                            "Komis dziekański": "",
                            "Powt. przedm. II poprawka": "",
                            "Powt. przedm. II komis": ""
                        }
                    ]
                },
                {
                    "SubjectName": "Podstawy organizacji i zarządzania",
                    "Records": [
                        {
                            "Forma zajęć": "A",
                            "Typ przedmiotu": "",
                            "Podtyp przedmiotu": "",
                            "Forma zaliczenia": "Z",
                            "Prowadzący": "kmdr por. mgr inż. Dariusz Stachowiak",
                            "Punkty ECTS": "0",
                            "Punkty ECTS za ostatnią ocenę": "50",
                            "Liczba godzin": "15",
                            "Zaliczony": "",
                            "Termin I": "3,0",
                            "Poprawkowy": "",
                            "Komis": "",
                            "Pow. przedm. I": "",
                            "Pow. przedm. II": "",
                            "Powt. przedm. poprawka": "",
                            "Powt. przedm. komis": "",
                            "Komis dziekański": "",
                            "Powt. przedm. II poprawka": "",
                            "Powt. przedm. II komis": ""
                        },
                        {
                            "Forma zajęć": "K",
                            "Typ przedmiotu": "",
                            "Podtyp przedmiotu": "",
                            "Forma zaliczenia": "KO",
                            "Prowadzący": "kmdr por. mgr inż. Dariusz Stachowiak",
                            "Punkty ECTS": "1",
                            "Punkty ECTS za ostatnią ocenę": "50",
                            "Liczba godzin": "0",
                            "Zaliczony": "",
                            "Termin I": "3,0",
                            "Poprawkowy": "",
                            "Komis": "",
                            "Pow. przedm. I": "",
                            "Pow. przedm. II": "",
                            "Powt. przedm. poprawka": "",
                            "Powt. przedm. komis": "",
                            "Komis dziekański": "",
                            "Powt. przedm. II poprawka": "",
                            "Powt. przedm. II komis": ""
                        }
                    ]
                },
                {
                    "SubjectName": "Problemy zawodowe i prawne informatyki",
                    "Records": [
                        {
                            "Forma zajęć": "A",
                            "Typ przedmiotu": "",
                            "Podtyp przedmiotu": "",
                            "Forma zaliczenia": "Z",
                            "Prowadzący": "dr inż. Łukasz Nozdrzykowski",
                            "Punkty ECTS": "0",
                            "Punkty ECTS za ostatnią ocenę": "80",
                            "Liczba godzin": "15",
                            "Zaliczony": "",
                            "Termin I": "4,5",
                            "Poprawkowy": "",
                            "Komis": "",
                            "Pow. przedm. I": "",
                            "Pow. przedm. II": "",
                            "Powt. przedm. poprawka": "",
                            "Powt. przedm. komis": "",
                            "Komis dziekański": "",
                            "Powt. przedm. II poprawka": "",
                            "Powt. przedm. II komis": ""
                        },
                        {
                            "Forma zajęć": "K",
                            "Typ przedmiotu": "",
                            "Podtyp przedmiotu": "",
                            "Forma zaliczenia": "KO",
                            "Prowadzący": "dr inż. Łukasz Nozdrzykowski",
                            "Punkty ECTS": "2",
                            "Punkty ECTS za ostatnią ocenę": "80",
                            "Liczba godzin": "0",
                            "Zaliczony": "",
                            "Termin I": "4,5",
                            "Poprawkowy": "",
                            "Komis": "",
                            "Pow. przedm. I": "",
                            "Pow. przedm. II": "",
                            "Powt. przedm. poprawka": "",
                            "Powt. przedm. komis": "",
                            "Komis dziekański": "",
                            "Powt. przedm. II poprawka": "",
                            "Powt. przedm. II komis": ""
                        }
                    ]
                },
                {
                    "SubjectName": "Analiza matematyczna",
                    "Records": [
                        {
                            "Forma zajęć": "A",
                            "Typ przedmiotu": "",
                            "Podtyp przedmiotu": "",
                            "Forma zaliczenia": "E",
                            "Prowadzący": "dr Anna Pańka",
                            "Punkty ECTS": "0",
                            "Punkty ECTS za ostatnią ocenę": "80",
                            "Liczba godzin": "30",
                            "Zaliczony": "",
                            "Termin I": "4,5",
                            "Poprawkowy": "",
                            "Komis": "",
                            "Pow. przedm. I": "",
                            "Pow. przedm. II": "",
                            "Powt. przedm. poprawka": "",
                            "Powt. przedm. komis": "",
                            "Komis dziekański": "",
                            "Powt. przedm. II poprawka": "",
                            "Powt. przedm. II komis": ""
                        },
                        {
                            "Forma zajęć": "C",
                            "Typ przedmiotu": "",
                            "Podtyp przedmiotu": "",
                            "Forma zaliczenia": "Z",
                            "Prowadzący": "mgr Kinga Kuzioła",
                            "Punkty ECTS": "0",
                            "Punkty ECTS za ostatnią ocenę": "80",
                            "Liczba godzin": "45",
                            "Zaliczony": "",
                            "Termin I": "4,5",
                            "Poprawkowy": "",
                            "Komis": "",
                            "Pow. przedm. I": "",
                            "Pow. przedm. II": "",
                            "Powt. przedm. poprawka": "",
                            "Powt. przedm. komis": "",
                            "Komis dziekański": "",
                            "Powt. przedm. II poprawka": "",
                            "Powt. przedm. II komis": ""
                        },
                        {
                            "Forma zajęć": "K",
                            "Typ przedmiotu": "",
                            "Podtyp przedmiotu": "",
                            "Forma zaliczenia": "KO",
                            "Prowadzący": "dr Anna Pańka",
                            "Punkty ECTS": "7",
                            "Punkty ECTS za ostatnią ocenę": "80",
                            "Liczba godzin": "0",
                            "Zaliczony": "",
                            "Termin I": "4,5",
                            "Poprawkowy": "",
                            "Komis": "",
                            "Pow. przedm. I": "",
                            "Pow. przedm. II": "",
                            "Powt. przedm. poprawka": "",
                            "Powt. przedm. komis": "",
                            "Komis dziekański": "",
                            "Powt. przedm. II poprawka": "",
                            "Powt. przedm. II komis": ""
                        }
                    ]
                },
                {
                    "SubjectName": "Fizyka",
                    "Records": [
                        {
                            "Forma zajęć": "A",
                            "Typ przedmiotu": "",
                            "Podtyp przedmiotu": "",
                            "Forma zaliczenia": "E",
                            "Prowadzący": "dr Agata Kowalska",
                            "Punkty ECTS": "0",
                            "Punkty ECTS za ostatnią ocenę": "60",
                            "Liczba godzin": "30",
                            "Zaliczony": "",
                            "Termin I": "3,5",
                            "Poprawkowy": "",
                            "Komis": "",
                            "Pow. przedm. I": "",
                            "Pow. przedm. II": "",
                            "Powt. przedm. poprawka": "",
                            "Powt. przedm. komis": "",
                            "Komis dziekański": "",
                            "Powt. przedm. II poprawka": "",
                            "Powt. przedm. II komis": ""
                        },
                        {
                            "Forma zajęć": "C",
                            "Typ przedmiotu": "",
                            "Podtyp przedmiotu": "",
                            "Forma zaliczenia": "Z",
                            "Prowadzący": "dr Agata Kowalska",
                            "Punkty ECTS": "0",
                            "Punkty ECTS za ostatnią ocenę": "70",
                            "Liczba godzin": "15",
                            "Zaliczony": "",
                            "Termin I": "4,0",
                            "Poprawkowy": "",
                            "Komis": "",
                            "Pow. przedm. I": "",
                            "Pow. przedm. II": "",
                            "Powt. przedm. poprawka": "",
                            "Powt. przedm. komis": "",
                            "Komis dziekański": "",
                            "Powt. przedm. II poprawka": "",
                            "Powt. przedm. II komis": ""
                        },
                        {
                            "Forma zajęć": "L",
                            "Typ przedmiotu": "",
                            "Podtyp przedmiotu": "",
                            "Forma zaliczenia": "Z",
                            "Prowadzący": "mgr inż. Agnieszka Szczepaniec",
                            "Punkty ECTS": "0",
                            "Punkty ECTS za ostatnią ocenę": "80",
                            "Liczba godzin": "30",
                            "Zaliczony": "",
                            "Termin I": "4,5",
                            "Poprawkowy": "",
                            "Komis": "",
                            "Pow. przedm. I": "",
                            "Pow. przedm. II": "",
                            "Powt. przedm. poprawka": "",
                            "Powt. przedm. komis": "",
                            "Komis dziekański": "",
                            "Powt. przedm. II poprawka": "",
                            "Powt. przedm. II komis": ""
                        },
                        {
                            "Forma zajęć": "K",
                            "Typ przedmiotu": "",
                            "Podtyp przedmiotu": "",
                            "Forma zaliczenia": "KO",
                            "Prowadzący": "dr Agata Kowalska",
                            "Punkty ECTS": "7",
                            "Punkty ECTS za ostatnią ocenę": "70",
                            "Liczba godzin": "0",
                            "Zaliczony": "",
                            "Termin I": "4,0",
                            "Poprawkowy": "",
                            "Komis": "",
                            "Pow. przedm. I": "",
                            "Pow. przedm. II": "",
                            "Powt. przedm. poprawka": "",
                            "Powt. przedm. komis": "",
                            "Komis dziekański": "",
                            "Powt. przedm. II poprawka": "",
                            "Powt. przedm. II komis": ""
                        }
                    ]
                },
                {
                    "SubjectName": "Wstęp do programowania",
                    "Records": [
                        {
                            "Forma zajęć": "A",
                            "Typ przedmiotu": "",
                            "Podtyp przedmiotu": "",
                            "Forma zaliczenia": "E",
                            "Prowadzący": "dr inż. Leszek Misztal",
                            "Punkty ECTS": "0",
                            "Punkty ECTS za ostatnią ocenę": "80",
                            "Liczba godzin": "30",
                            "Zaliczony": "",
                            "Termin I": "4,5",
                            "Poprawkowy": "",
                            "Komis": "",
                            "Pow. przedm. I": "",
                            "Pow. przedm. II": "",
                            "Powt. przedm. poprawka": "",
                            "Powt. przedm. komis": "",
                            "Komis dziekański": "",
                            "Powt. przedm. II poprawka": "",
                            "Powt. przedm. II komis": ""
                        },
                        {
                            "Forma zajęć": "L",
                            "Typ przedmiotu": "",
                            "Podtyp przedmiotu": "",
                            "Forma zaliczenia": "Z",
                            "Prowadzący": "mgr inż. Filip Majewski",
                            "Punkty ECTS": "0",
                            "Punkty ECTS za ostatnią ocenę": "90",
                            "Liczba godzin": "30",
                            "Zaliczony": "",
                            "Termin I": "5,0",
                            "Poprawkowy": "",
                            "Komis": "",
                            "Pow. przedm. I": "",
                            "Pow. przedm. II": "",
                            "Powt. przedm. poprawka": "",
                            "Powt. przedm. komis": "",
                            "Komis dziekański": "",
                            "Powt. przedm. II poprawka": "",
                            "Powt. przedm. II komis": ""
                        },
                        {
                            "Forma zajęć": "K",
                            "Typ przedmiotu": "",
                            "Podtyp przedmiotu": "",
                            "Forma zaliczenia": "KO",
                            "Prowadzący": "dr inż. Leszek Misztal",
                            "Punkty ECTS": "7",
                            "Punkty ECTS za ostatnią ocenę": "90",
                            "Liczba godzin": "0",
                            "Zaliczony": "",
                            "Termin I": "5,0",
                            "Poprawkowy": "",
                            "Komis": "",
                            "Pow. przedm. I": "",
                            "Pow. przedm. II": "",
                            "Powt. przedm. poprawka": "",
                            "Powt. przedm. komis": "",
                            "Komis dziekański": "",
                            "Powt. przedm. II poprawka": "",
                            "Powt. przedm. II komis": ""
                        }
                    ]
                },
                {
                    "SubjectName": "Wstęp do algorytmizacji",
                    "Records": [
                        {
                            "Forma zajęć": "A",
                            "Typ przedmiotu": "",
                            "Podtyp przedmiotu": "",
                            "Forma zaliczenia": "Z",
                            "Prowadzący": "dr Tomasz Wierenko",
                            "Punkty ECTS": "0",
                            "Punkty ECTS za ostatnią ocenę": "60",
                            "Liczba godzin": "15",
                            "Zaliczony": "",
                            "Termin I": "3,5",
                            "Poprawkowy": "",
                            "Komis": "",
                            "Pow. przedm. I": "",
                            "Pow. przedm. II": "",
                            "Powt. przedm. poprawka": "",
                            "Powt. przedm. komis": "",
                            "Komis dziekański": "",
                            "Powt. przedm. II poprawka": "",
                            "Powt. przedm. II komis": ""
                        },
                        {
                            "Forma zajęć": "C",
                            "Typ przedmiotu": "",
                            "Podtyp przedmiotu": "",
                            "Forma zaliczenia": "Z",
                            "Prowadzący": "dr Tomasz Wierenko",
                            "Punkty ECTS": "0",
                            "Punkty ECTS za ostatnią ocenę": "70",
                            "Liczba godzin": "15",
                            "Zaliczony": "",
                            "Termin I": "4,0",
                            "Poprawkowy": "",
                            "Komis": "",
                            "Pow. przedm. I": "",
                            "Pow. przedm. II": "",
                            "Powt. przedm. poprawka": "",
                            "Powt. przedm. komis": "",
                            "Komis dziekański": "",
                            "Powt. przedm. II poprawka": "",
                            "Powt. przedm. II komis": ""
                        },
                        {
                            "Forma zajęć": "K",
                            "Typ przedmiotu": "",
                            "Podtyp przedmiotu": "",
                            "Forma zaliczenia": "KO",
                            "Prowadzący": "dr Tomasz Wierenko",
                            "Punkty ECTS": "3",
                            "Punkty ECTS za ostatnią ocenę": "60",
                            "Liczba godzin": "0",
                            "Zaliczony": "",
                            "Termin I": "3,5",
                            "Poprawkowy": "",
                            "Komis": "",
                            "Pow. przedm. I": "",
                            "Pow. przedm. II": "",
                            "Powt. przedm. poprawka": "",
                            "Powt. przedm. komis": "",
                            "Komis dziekański": "",
                            "Powt. przedm. II poprawka": "",
                            "Powt. przedm. II komis": ""
                        }
                    ]
                },
                {
                    "SubjectName": "Innowacyjne projekty informatyczne",
                    "Records": [
                        {
                            "Forma zajęć": "A",
                            "Typ przedmiotu": "",
                            "Podtyp przedmiotu": "",
                            "Forma zaliczenia": "Z",
                            "Prowadzący": "dr inż. kpt.ż.w. Piotr Wołejsza",
                            "Punkty ECTS": "0",
                            "Punkty ECTS za ostatnią ocenę": "90",
                            "Liczba godzin": "30",
                            "Zaliczony": "",
                            "Termin I": "5,0",
                            "Poprawkowy": "",
                            "Komis": "",
                            "Pow. przedm. I": "",
                            "Pow. przedm. II": "",
                            "Powt. przedm. poprawka": "",
                            "Powt. przedm. komis": "",
                            "Komis dziekański": "",
                            "Powt. przedm. II poprawka": "",
                            "Powt. przedm. II komis": ""
                        },
                        {
                            "Forma zajęć": "K",
                            "Typ przedmiotu": "",
                            "Podtyp przedmiotu": "",
                            "Forma zaliczenia": "KO",
                            "Prowadzący": "dr inż. kpt.ż.w. Piotr Wołejsza",
                            "Punkty ECTS": "2",
                            "Punkty ECTS za ostatnią ocenę": "90",
                            "Liczba godzin": "0",
                            "Zaliczony": "",
                            "Termin I": "5,0",
                            "Poprawkowy": "",
                            "Komis": "",
                            "Pow. przedm. I": "",
                            "Pow. przedm. II": "",
                            "Powt. przedm. poprawka": "",
                            "Powt. przedm. komis": "",
                            "Komis dziekański": "",
                            "Powt. przedm. II poprawka": "",
                            "Powt. przedm. II komis": ""
                        }
                    ]
                }
            ]
        }
    ]
}